{
    "code": "mmx-hero",
    "type": "Z",
    "is_global": false,
    "active": true,
    "attributes": [
        {
            "name": "type",
            "value": "text/css"
        },
        {
            "name": "media",
            "value": "all"
        },
        {
            "name": "rel",
            "value": "stylesheet"
        },
        {
            "name": "integrity",
            "value": "sha256-zxjptL6jOH9ngt+/PPOfZgvxNNeu4fBSFYdW7t+5c78= sha384-Q0XDroUtaN9WAMQ7Jatju4hCM1QiJJ9a9Fa/yiDdx2SBrJc+Md83diegyprVPrdP sha512-1qXQKWNOOHXljWyiB2XCTos4xPiP1J8waTHK7ZFIulwhkjQUMXUJIU0Eguh7VkkzgH0jnKbEFx8U4utd0K2uwA=="
        },
        {
            "name": "crossorigin",
            "value": "anonymous"
        }
    ],
    "linked_pages": []
}